<?xml version="1.0" encoding="utf-8"?>
<!DOCTYPE hibernate-mapping PUBLIC "-//Hibernate/Hibernate Mapping DTD 3.0//EN"
"http://hibernate.sourceforge.net/hibernate-mapping-3.0.dtd">
<!-- 
    Mapping file autogenerated by MyEclipse Persistence Tools
-->
<hibernate-mapping>
    <class name="com.rural.bean.CountryFil" table="CountryFil" schema="dbo" catalog="RuralConstruction">
        <id name="countryFilId" type="integer">
            <column name="CountryFilID" />
            <generator class="native" />
        </id>
        <many-to-one name="countryBasicInfo" class="com.rural.bean.CountryBasicInfo" fetch="select">
            <column name="CountryBasicInfoID" />
        </many-to-one>
        <many-to-one name="goveFilClfy" class="com.rural.bean.GoveFilClfy" fetch="select">
            <column name="GoveFilClfyID" />
        </many-to-one>
        <property name="countryFilNum" type="string">
            <column name="CountryFilNum" unique="true" />
        </property>
        <property name="countryFilName" type="string">
            <column name="CountryFilName" />
        </property>
        <property name="countryFilIdef" type="string">
            <column name="CountryFilIdef" />
        </property>
        <property name="countryFilMadTim" type="timestamp">
            <column name="CountryFilMadTim" length="23" />
        </property>
        <property name="countryFilPubComp" type="string">
            <column name="CountryFilPubComp" />
        </property>
        <property name="countryFilExpl" type="string">
            <column name="CountryFilExpl" />
        </property>
    </class>
</hibernate-mapping>
